{"8-bit":{"female":"85osbf33","male":"8qkd7bbf","UCexist":false},"baby":{"female":"zdjxvmds","male":"fwd63758","UCexist":true},"biscuit":{"female":"obskdlzs","male":"v7c37nhx","UCexist":false},"blue":{"female":"xhsz43wm","male":"7ls55f33","UCexist":true},"brown":{"female":"wdoq9mjq","male":"ll3hvfv3","UCexist":true},"camouflage":{"female":"kzqqbgns","male":"6wn8czsl","UCexist":false},"checkered":{"female":"6w93w6zs","male":"9hn28k82","UCexist":false},"chocolate":{"female":"sdkfxk3c","male":"7m3loffw","UCexist":false},"christmas":{"female":"4sr64zvh","male":"4jtro6vw","UCexist":false},"cloud":{"female":"5rosk4vm","male":"b3rmgk5b","UCexist":true},"custard":{"female":"9r5n36wq","male":"2xr8z3xr","UCexist":false},"darigan":{"female":"922corts","male":"v26598dx","UCexist":true},"desert":{"female":"mocf4ofr","male":"4q33j2ql","UCexist":true},"disco":{"female":"d55l4nbk","male":"4s2j32w4","UCexist":true},"electric":{"female":"n7klv2k6","male":"5f2flb9t","UCexist":false},"eventide":{"female":"7fwdxj26","male":"t2tom5k8","UCexist":false},"faerie":{"female":"63q3j9cn","male":"3zjz766w","UCexist":false},"fire":{"female":"kl5n7vhr","male":"g73bws49","UCexist":false},"ghost":{"female":"jj2645rn","male":"nhnnsbv4","UCexist":true},"glowing":{"female":"dgs2b3dr","male":"lx4dr98c","UCexist":true},"green":{"female":"ojoz57gz","male":"dz5dwsbx","UCexist":true},"grey":{"female":"89xkx9qv","male":"mcn9bbdd","UCexist":false},"halloween":{"female":"wflb8m57","male":"r49jcwzc","UCexist":false},"ice":{"female":"xx7sqc7x","male":"rbf5zm2s","UCexist":true},"island":{"female":"mdl4wd33","male":"f6tbhmzb","UCexist":true},"jelly":{"female":"76mf2qwv","male":"mj847dhj","UCexist":false},"magma":{"female":"cr5wf9zq","male":"tm3cjvx5","UCexist":false},"maractite":{"female":"zw2vs9tl","male":"6tshthhr","UCexist":false},"maraquan":{"female":"76j6b2vs","male":"z5dw7ln7","UCexist":true},"mutant":{"female":"zkdrl9qc","male":"xx8g8jjb","UCexist":true},"orange":{"female":"38zn948l","male":"kxd8lmg3","UCexist":true},"pastel":{"female":"h6ho36co","male":"rd59sf2o","UCexist":false},"pink":{"female":"j3897584","male":"56mg63ls","UCexist":false},"pirate":{"female":"n5xbsv7x","male":"t5445wk2","UCexist":false},"plushie":{"female":"wlqccb7c","male":"6bvsvhok","UCexist":true},"polka dot":{"female":"sxsmfj74","male":"bkb5tobd","UCexist":false},"purple":{"female":"jh2d446j","male":"b7hdlxmo","UCexist":true},"rainbow":{"female":"rgj9qhk8","male":"8krl67r4","UCexist":true},"red":{"female":"dnm7fcfo","male":"jsfvcqwt","UCexist":true},"relic":{"female":"crxjb3dq","male":"j3b3m522","UCexist":false},"robot":{"female":"ms2tfndd","male":"vm7l8hwd","UCexist":false},"royalboy":{"female":"r72782g9","male":"ks8gv3cf","UCexist":false},"royalgirl":{"female":"vc63srvr","male":"t6zw7s5m","UCexist":false},"shadow":{"female":"svdkvz58","male":"ltwqhvb6","UCexist":true},"skunk":{"female":"bcl93vqh","male":"vtvd9btz","UCexist":false},"speckled":{"female":"7mjbdz2v","male":"skd55v3k","UCexist":false},"split":{"female":"hxd2mk2h","male":"xh4hf2dr","UCexist":false},"sponge":{"female":"tvjg6zdw","male":"q3tk6hs6","UCexist":false},"spotted":{"female":"d4lh843o","male":"h3k6q7hz","UCexist":false},"starry":{"female":"kf8zlxgx","male":"5n9cbjws","UCexist":true},"stealthy":{"female":"4633tno4","male":"j8ntdbj8","UCexist":false},"steampunk":{"female":"m8bthvfn","male":"gb53sco2","UCexist":false},"striped":{"female":"b4965f5w","male":"23wb8n2f","UCexist":true},"toy":{"female":"zfqt3ss9","male":"9m9zt7s7","UCexist":false},"transparent":{"female":"88lxkt7d","male":"rvl4oqo2","UCexist":false},"tyrannian":{"female":"zo8oj8xf","male":"l6dx2xkv","UCexist":false},"water":{"female":"7v8ogotm","male":"8dr32h7j","UCexist":false},"white":{"female":"hw54wnsc","male":"hvvlj8r9","UCexist":true},"wraith":{"female":"vxknf732","male":"lmj98528","UCexist":false},"yellow":{"female":"hgfh65d6","male":"z24m7h7l","UCexist":true},"zombie":{"female":"nbfm44nm","male":"htx3r9hv","UCexist":false}}